locknessie/__init__.py
locknessie/cli.py
locknessie/logger.py
locknessie/main.py
locknessie/server.py
locknessie/settings.py
locknessie/auth_providers/__init__.py
locknessie/auth_providers/base.py
locknessie/auth_providers/microsoft.py
locknessie-1.2.3.dist-info/METADATA
locknessie-1.2.3.dist-info/WHEEL
locknessie-1.2.3.dist-info/entry_points.txt
locknessie-1.2.3.dist-info/RECORD
