Metadata-Version: 2.4
Name: locknessie
Version: 1.2.3
Summary: LockNessie provides a client and server pair for authentication to Nessie with OpenID.
Requires-Python: >=3.8
Requires-Dist: click>=7.0
Requires-Dist: fastapi>=0.68.0
Requires-Dist: jinja2>=2.11.0
Requires-Dist: pydantic-settings>=1.8.0
Requires-Dist: pydantic>=1.8.0
Requires-Dist: pyjwt>=2.0.0
Requires-Dist: requests>=2.25.0
Requires-Dist: uvicorn>=0.15.0
Provides-Extra: keycloak
Requires-Dist: python-keycloak>=3.0.0; extra == 'keycloak'
Provides-Extra: microsoft
Requires-Dist: msal>=1.20.0; extra == 'microsoft'
